skyclean/__init__.py
skyclean/cmb_data.py
skyclean/CMB_data/CMB_data.py
skyclean/CMB_data/__init__.py
skyclean/CMB_data/cmb_data.py
skyclean/CMB_data/test.py
skyclean/tools/ILC_functions.py
skyclean/tools/__init__.py
skyclean/tools/drawing_functions.py
skyclean/tools/map_functions.py
skyclean/tools/useful_functions.py
skyclean/tools/wavelets_functions.py
skyclean-0.0.4.2.dist-info/LICENSE
skyclean-0.0.4.2.dist-info/METADATA
skyclean-0.0.4.2.dist-info/WHEEL
skyclean-0.0.4.2.dist-info/top_level.txt
skyclean-0.0.4.2.dist-info/RECORD
